topl/__init__.py
topl/__main__.py
topl/_version.py
topl/cli.py
topl/constants.py
topl/core.py
topl/exceptions.py
topl/py.typed
topl/types.py
topl/utils.py
toml_topl-1.0.5.dist-info/METADATA
toml_topl-1.0.5.dist-info/WHEEL
toml_topl-1.0.5.dist-info/entry_points.txt
toml_topl-1.0.5.dist-info/licenses/LICENSE
toml_topl-1.0.5.dist-info/RECORD
